libcaf/__init__.py
libcaf/base.py
libCAF-0.1.0b0.dist-info/LICENSE
libCAF-0.1.0b0.dist-info/METADATA
libCAF-0.1.0b0.dist-info/WHEEL
libCAF-0.1.0b0.dist-info/top_level.txt
libCAF-0.1.0b0.dist-info/RECORD
