Metadata-Version: 2.1
Name: libCAF
Version: 0.1.0b0
Summary: Parser and Builder classes related to Apple's Core Audio Format (.caf).
Author-email: MatrixEditor <not@supported.com>
Project-URL: homepage, https://github.com/JustHexData/CAF
Project-URL: repository, https://github.com/JustHexData/CAF
Project-URL: documentation, https://justhexdata.github.io/CAF
Classifier: Development Status :: 4 - Beta
License-File: LICENSE
